Authors
ChangeLog
License
MANIFEST
setup.py
RosterServer.egg-info/PKG-INFO
RosterServer.egg-info/SOURCES.txt
RosterServer.egg-info/dependency_links.txt
RosterServer.egg-info/requires.txt
RosterServer.egg-info/top_level.txt
docs/html/.buildinfo
docs/html/genindex.html
docs/html/index.html
docs/html/objects.inv
docs/html/py-modindex.html
docs/html/roster_server.html
docs/html/search.html
docs/html/searchindex.js
docs/html/_modules/index.html
docs/html/_modules/roster_server/__init__.html
docs/html/_modules/roster_server/auth_pam.html
docs/html/_modules/roster_server/credentials.html
docs/html/_modules/roster_server/general_ldap.html
docs/html/_modules/roster_server/server.html
docs/html/_modules/roster_server/ssl_xml_rpc_lib.html
docs/html/_sources/index.txt
docs/html/_sources/roster_server.txt
docs/html/_static/ajax-loader.gif
docs/html/_static/basic.css
docs/html/_static/comment-bright.png
docs/html/_static/comment-close.png
docs/html/_static/comment.png
docs/html/_static/default.css
docs/html/_static/doctools.js
docs/html/_static/down-pressed.png
docs/html/_static/down.png
docs/html/_static/file.png
docs/html/_static/jquery.js
docs/html/_static/minus.png
docs/html/_static/plus.png
docs/html/_static/pygments.css
docs/html/_static/searchtools.js
docs/html/_static/sidebar.js
docs/html/_static/underscore.js
docs/html/_static/up-pressed.png
docs/html/_static/up.png
docs/html/_static/websupport.js
roster_server/__init__.py
roster_server/auth_pam.py
roster_server/credentials.py
roster_server/general_ldap.py
roster_server/server.py
roster_server/ssl_xml_rpc_lib.py
scripts/rosterd